{"data":[
  {
    "name": "张雪",
    "content": "同意",
    "submitTime": "2019-07-25"
  },{
    "name": "赵辉",
    "content": "不同意",
    "submitTime": "2019-07-25"
  },{
    "name": "张雪",
    "content": "同意",
    "submitTime": "2019-07-25"
  },{
    "name": "赵辉",
    "content": "不同意",
    "submitTime": "2019-07-25"
  },{
    "name": "张雪",
    "content": "同意",
    "submitTime": "2019-07-25"
  },{
    "name": "赵辉",
    "content": "不同意",
    "submitTime": "2019-07-25"
  },{
    "name": "张雪",
    "content": "同意",
    "submitTime": "2019-07-25"
  },{
    "name": "赵辉",
    "content": "不同意",
    "submitTime": "2019-07-25"
  },{
    "name": "赵辉",
    "content": "不同意",
    "submitTime": "2019-07-25"
  },{
    "name": "张雪",
    "content": "同意",
    "submitTime": "2019-07-25"
  },{
    "name": "赵辉",
    "content": "不同意",
    "submitTime": "2019-07-25"
  }
],"totalSize":11
}