{"list":
[
  {
    "date": "2016-05-02",
    "name": "20190529测试",
    "deptName": "中共桂花社区第一支部委员会",
    "keys": "两学一做,纪律处分",
    "type": "支部党员大会",
    "time": "2019-05-20 17:00-2019-05-20 21:00",
    "address": "广东省广州市天河区",
    "status": "已关闭"
  }, {
    "date": "2016-05-02",
    "name": "某支部全体委员大会",
    "deptName": "中共桂花社区第一支部委员会",
    "keys": "民主评议党员,发展党员",
    "type": "支部委员会",
    "time": "2019-05-20 17:00-2019-05-20 21:00",
    "address": "广东省广州市越秀区东湖北路30号",
    "status": "已关闭"
  }, {
    "date": "2016-05-02",
    "name": "某支部全体委员大会",
    "deptName": "中共桂花社区第一支部委员会",
    "keys": "党内慰问",
    "type": "支部委员会",
    "time": "2019-05-20 17:00-2019-05-20 21:00",
    "address": "广东省广州市越秀区东湖北路30号",
    "status": "已关闭"
  }, {
    "date": "2016-05-02",
    "name": "第十五届三中全会",
    "deptName": "中共兰贵社区第二支部委员会",
    "keys": "纪律处分,谈心谈话,",
    "type": "支部委员会",
    "time": "2019-05-20 17:00-2019-05-20 21:00",
    "address": "广东省广州市天河区员村一横路7号大院",
    "status": "已关闭"
  },
  {
    "date": "2016-05-02",
    "name": "会议",
    "deptName": "中共兰贵社区第二支部委员会",
    "keys": "纪律处分,谈心谈话,",
    "type": "支部委员会",
    "time": "2019-05-20 17:00-2019-05-20 21:00",
    "address": "广东省广州市天河区员村一横路7号大院",
    "status": "草稿"
  }, {
    "date": "2016-05-02",
    "name": "安吉会议",
    "deptName": "中共兰贵社区第二支部委员会",
    "keys": "纪律处分,谈心谈话,",
    "type": "支部委员会",
    "time": "2019-05-20 17:00-2019-05-20 21:00",
    "address": "广东省广州市天河区员村一横路7号大院",
    "status": "已关闭"
  }, {
    "date": "2016-05-02",
    "name": "兰贵社区第二支部会议",
    "deptName": "中共兰贵社区第二支部委员会",
    "keys": "两学一做",
    "type": "支部委员会",
    "time": "2019-05-20 17:00-2019-05-20 21:00",
    "address": "广东省广州市天河区黄埔大道西120号",
    "status": "已关闭"
  }, {
    "date": "2016-05-02",
    "name": "第十五届三中全会",
    "deptName": "中共兰贵社区第二支部委员会",
    "keys": "党内表彰,纪律处分",
    "type": "支部委员会",
    "time": "2019-05-20 17:00-2019-05-20 21:00",
    "address": "广东省广州市天河区黄埔大道西120号",
    "status": "已关闭"
  },
  {
    "date": "2016-05-02",
    "name": "主题教育",
    "deptName": "中共兰贵社区第六支部委员会",
    "keys": "党内表彰,纪律处分",
    "type": "支部委员会",
    "time": "2019-05-20 17:00-2019-05-20 21:00",
    "address": "广东省广州市天河区黄埔大道西120号",
    "status": "已关闭"
  }, {
    "date": "2016-05-02",
    "name": "普惠政策",
    "deptName": "中共兰贵社区第六支部委员会",
    "keys": "党内表彰,纪律处分",
    "type": "支部委员会",
    "time": "2019-05-20 17:00-2019-05-20 21:00",
    "address": "广东省广州市天河区黄埔大道西120号",
    "status": "已关闭"
  }, {
    "date": "2016-05-02",
    "name": "【0724】支部党员大会会（未开始）中国特色社会主义是历史的结论、人民的选择",
    "deptName": "中共兰贵社区第一支部委员会",
    "keys": "发展党员",
    "type": "支部委员会",
    "time": "2019-05-20 17:00-2019-05-20 21:00",
    "address": "广东省广州市越秀区环市西路181号",
    "status": "已关闭"
  }, {
    "date": "2016-05-02",
    "name": "安全测试",
    "deptName": "中共兰贵社区第一支部委员会",
    "keys": "发展党员",
    "type": "支部委员会",
    "time": "2019-05-20 17:00-2019-05-20 21:00",
    "address": "广东省广州市越秀区环市西路181号",
    "status": "已关闭"
  },{
    "date": "2016-05-02",
    "name": "支部党员大会（已结束）中国特色社会主义是历史的结论、人民的选择",
    "deptName": "中共兰贵社区第一支部委员会",
    "keys": "发展党员",
    "type": "支部委员会",
    "time": "2019-05-20 17:00-2019-05-20 21:00",
    "address": "广东省广州市越秀区环市西路181号",
    "status": "已关闭"
  }, {
    "date": "2016-05-02",
    "name": "海德堡的",
    "deptName": "中共兰贵社区第一支部委员会",
    "keys": "换届,两学一做",
    "type": "支部委员会",
    "time": "2019-05-20 17:00-2019-05-20 21:00",
    "address": "广东省广州市越秀区环市西路181号",
    "status": "已关闭"
  }, {
    "date": "2016-05-02",
    "name": "支委会",
    "deptName": "中共兰贵社区第一支部委员会",
    "keys": "换届,两学一做",
    "type": "支部委员会",
    "time": "2019-05-20 17:00-2019-05-20 21:00",
    "address": "广东省广州市越秀区环市西路181号",
    "status": "已关闭"
  }, {
    "date": "2016-05-02",
    "name": "何惧于心",
    "deptName": "中共兰贵社区第一支部委员会",
    "keys": "党内慰问,谈心谈话",
    "type": "支部委员会",
    "time": "2019-05-20 17:00-2019-05-20 21:00",
    "address": "广东省广州市天河区黄埔大道西120号",
    "status": "已关闭"
  }
],

  "totalSize": 16,
  "tableSet": {
      "tableSize": "大",
      "pageSize": 100,
      "caption": "测试",
      "tableScale": 100,
      "defaultSort": {"prop": "deptName",
        "order": ""
      }
  },
  "columnsData":[
    {
      "label": "会议名称",
      "prop": "name",
      "width": "20%",
      "fixed": "left",
      "show": true,
      "sortable": true
    },
    {
      "label": "所属党组织",
      "prop": "deptName",
      "width":130,
      "show": true
    },
    {
      "label": "会议关键词",
      "prop": "keys",
      "show": false
    },
    {
      "label": "会议类型",
      "prop": "type",
      "show": false
    },
    {
      "label": "会议时间",
      "prop": "time",
      "show": false
    },
    {
      "label": "活动地点",
      "prop": "address",
      "show": false
    },
    {
      "label": "状态",
      "prop": "status",
      "show": false
    },
    {
      "label": "操作",
      "prop": "opts",
      "show": false
    }
  ]
}
